fastpkg.py
fastpkg-0.0.1.dist-info/METADATA
fastpkg-0.0.1.dist-info/WHEEL
fastpkg-0.0.1.dist-info/entry_points.txt
fastpkg-0.0.1.dist-info/licenses/LICENSE
fastpkg-0.0.1.dist-info/RECORD
